setup.py
digURLExtractor/__init__.py
digURLExtractor/url_extractor.py
digURLExtractor/ze_url_extractor.py
digURLExtractor.egg-info/PKG-INFO
digURLExtractor.egg-info/SOURCES.txt
digURLExtractor.egg-info/dependency_links.txt
digURLExtractor.egg-info/requires.txt
digURLExtractor.egg-info/top_level.txt
test/__init__.py
test/test_url_extractor.py