Metadata-Version: 1.1
Name: digURLExtractor
Version: 0.3.0
Summary: digURLExtractor
Home-page: https://github.com/usc-isi-i2/dig-url-extractor
Author: Lingzhe Teng
Author-email: zwein27@gmail.com
License: UNKNOWN
Download-URL: https://github.com/usc-isi-i2/dig-url-extractor
Keywords: url,extractor
Platform: UNKNOWN
